linkedlist_mod/__init__.py
linkedlist_mod/linkedlist.py
single_linkedlist_module/__init__.py
single_linkedlist_module/linkedlist.py
single_linkedlist_module-0.1.0.dist-info/METADATA
single_linkedlist_module-0.1.0.dist-info/WHEEL
single_linkedlist_module-0.1.0.dist-info/top_level.txt
single_linkedlist_module-0.1.0.dist-info/RECORD
