Metadata-Version: 2.1
Name: single-linkedlist-module
Version: 0.1.0
Summary: Single LinkedList library
Home-page: UNKNOWN
Author: Me
Author-email: UNKNOWN
License: MIT
Platform: UNKNOWN
